QuotesEngine/__init__.py
QuotesEngine/quotes.py
QuotesEngine/simple.py
QuotesEngine-6.0.dist-info/LICENSE
QuotesEngine-6.0.dist-info/METADATA
QuotesEngine-6.0.dist-info/WHEEL
QuotesEngine-6.0.dist-info/top_level.txt
QuotesEngine-6.0.dist-info/RECORD
