Metadata-Version: 2.1
Name: QuotesEngine
Version: 6.0
Summary: A Python library to display some random motivation quotes.
Author: Sridharan
Author-email: sridharansri2312@gmail.com
Classifier: Programming Language :: Python :: 3
Classifier: License :: OSI Approved :: MIT License
Classifier: Operating System :: OS Independent
Requires-Python: >=3.6
License-File: LICENSE
